cars/__init__.py
cars/fiat.py
cars/nissan.py
cars/sample.py
shopping/__init__.py
shopping/cars_enum.py
shopping/list_cars.py
Exercise_publishing_package-0.0.1.dist-info/LICENSE.txt
Exercise_publishing_package-0.0.1.dist-info/METADATA
Exercise_publishing_package-0.0.1.dist-info/WHEEL
Exercise_publishing_package-0.0.1.dist-info/top_level.txt
Exercise_publishing_package-0.0.1.dist-info/RECORD
