Metadata-Version: 2.1
Name: Exercise-publishing-package
Version: 0.0.1
Summary: Not needed
Home-page: UNKNOWN
Author: auguste
Author-email: auguste.nausedaite@gmail.com
License: UNKNOWN
Platform: UNKNOWN
Requires-Python: >=3.6
